lambdawaker/draw/card_background/__init__.py
lambdawaker/draw/card_background/type_a.py
lambdawaker_draw_card_backgorund-0.1.0.dist-info/licenses/LICENSE
lambdawaker_draw_card_backgorund-0.1.0.dist-info/METADATA
lambdawaker_draw_card_backgorund-0.1.0.dist-info/WHEEL
lambdawaker_draw_card_backgorund-0.1.0.dist-info/top_level.txt
lambdawaker_draw_card_backgorund-0.1.0.dist-info/RECORD
