Metadata-Version: 2.4
Name: lambdawaker-draw-card_backgorund
Version: 0.1.0
Summary: Utilities to generate card backgrounds (Type A) using concentric polygons.
Author: LambdaWaker
License: MIT License
Project-URL: Homepage, https://github.com/your-org/py_lw_card_background
Project-URL: Repository, https://github.com/your-org/py_lw_card_background
Keywords: graphics,Pillow,aggdraw,cards,background,polygons
Classifier: Programming Language :: Python :: 3
Classifier: Programming Language :: Python :: 3 :: Only
Classifier: Operating System :: OS Independent
Classifier: Topic :: Multimedia :: Graphics
Requires-Python: >=3.8
License-File: LICENSE
Requires-Dist: Pillow>=9.0
Requires-Dist: aggdraw>=1.3.18
Requires-Dist: lambdawaker-draw-fill
Dynamic: license-file
